sailor/__init__.py
sailor/_base/__init__.py
sailor/_base/fetch.py
sailor/_base/masterdata.py
sailor/assetcentral/__init__.py
sailor/assetcentral/constants.py
sailor/assetcentral/equipment.py
sailor/assetcentral/failure_mode.py
sailor/assetcentral/functional_location.py
sailor/assetcentral/group.py
sailor/assetcentral/indicators.py
sailor/assetcentral/location.py
sailor/assetcentral/model.py
sailor/assetcentral/notification.py
sailor/assetcentral/system.py
sailor/assetcentral/utils.py
sailor/assetcentral/workorder.py
sailor/pai/__init__.py
sailor/pai/alert.py
sailor/pai/constants.py
sailor/pai/utils.py
sailor/sap_iot/__init__.py
sailor/sap_iot/_common.py
sailor/sap_iot/fetch.py
sailor/sap_iot/fetch_aggregates.py
sailor/sap_iot/wrappers.py
sailor/sap_iot/write.py
sailor/utils/__init__.py
sailor/utils/config.py
sailor/utils/plot_helper.py
sailor/utils/timestamps.py
sailor/utils/utils.py
sailor/utils/oauth_wrapper/OAuthServiceImpl.py
sailor/utils/oauth_wrapper/__init__.py
sailor/utils/oauth_wrapper/clients.py
sailor/utils/oauth_wrapper/scope_config.py
sailor-1.9.0.dist-info/LICENSE
sailor-1.9.0.dist-info/METADATA
sailor-1.9.0.dist-info/WHEEL
sailor-1.9.0.dist-info/top_level.txt
sailor-1.9.0.dist-info/RECORD
