Metadata-Version: 2.1
Name: sailor
Version: 1.9.0
Summary: Easily access data from your SAP Digital Supply Chain software products for data science projects like predictive maintenance or master data analysis.
Home-page: https://github.com/SAP/project-sailor
Author: DSC Data Science Team
Author-email: project.sailor@sap.com
Project-URL: Documentation, https://sap.github.io/project-sailor
Project-URL: Blog, https://blogs.sap.com/
Classifier: Development Status :: 4 - Beta
Classifier: License :: OSI Approved :: Apache Software License
Classifier: Programming Language :: Python :: 3.8
Classifier: Programming Language :: Python :: 3.9
Classifier: Programming Language :: Python :: 3.10
Requires-Python: >=3.8
License-File: LICENSE
Requires-Dist: furl (>=2.1.3)
Requires-Dist: pyjwt (>=2.4.0)
Requires-Dist: matplotlib
Requires-Dist: pandas (>=1.2.0)
Requires-Dist: plotnine
Requires-Dist: pyyaml
Requires-Dist: rauth
Requires-Dist: requests
Requires-Dist: scikit-learn
Requires-Dist: cachetools
Requires-Dist: isodate
